DroidRpc/__init__.py
DroidRpc/droid_grpc.py
DroidRpc/droid_pb2.py
DroidRpc/main.py
DroidRpc/raw_client_example.py
DroidRpc/formatting/__init__.py
DroidRpc/formatting/converter.py
DroidRpc/formatting/datetime.py
DroidRpc-1.6.4.dist-info/METADATA
DroidRpc-1.6.4.dist-info/WHEEL
DroidRpc-1.6.4.dist-info/top_level.txt
DroidRpc-1.6.4.dist-info/RECORD
